pdfshift/__init__.py
pdfshift/errors.py
pdfshift-1.0.4.dist-info/LICENSE.txt
pdfshift-1.0.4.dist-info/METADATA
pdfshift-1.0.4.dist-info/RECORD
pdfshift-1.0.4.dist-info/WHEEL
pdfshift-1.0.4.dist-info/top_level.txt
